fnet_args/__init__.py
fnet_args/cli/__init__.py
fnet_args/cli/index.py
fnet_args/lib/__init__.py
fnet_args/lib/index.py
fnet_args-0.1.29.dist-info/METADATA
fnet_args-0.1.29.dist-info/WHEEL
fnet_args-0.1.29.dist-info/entry_points.txt
fnet_args-0.1.29.dist-info/top_level.txt
fnet_args-0.1.29.dist-info/RECORD
