Metadata-Version: 2.1
Name: fnet_args
Version: 0.1.29
Requires-Python: >=3.12
Requires-Dist: pyyaml
Requires-Dist: jsonschema
Requires-Dist: deepmerge
Requires-Dist: rich
